routeros_scanner/.DS_Store
routeros_scanner/__init__.py
routeros_scanner/main.py
routeros_scanner/nvd.py
routeros_scanner/query_nvd.py
routeros_scanner/commands/basecommand.py
routeros_scanner/commands/dns.py
routeros_scanner/commands/files.py
routeros_scanner/commands/fwnat.py
routeros_scanner/commands/fwrules.py
routeros_scanner/commands/ports.py
routeros_scanner/commands/proxy.py
routeros_scanner/commands/scheduler.py
routeros_scanner/commands/socks.py
routeros_scanner/commands/users.py
routeros_scanner/commands/version.py
routeros_scanner-1.8.dist-info/METADATA
routeros_scanner-1.8.dist-info/WHEEL
routeros_scanner-1.8.dist-info/licenses/LICENSE
routeros_scanner-1.8.dist-info/RECORD
