Metadata-Version: 2.1
Name: routeros_scanner
Version: 1.8
Summary: Forensics tool for Mikrotik devices.
Project-URL: Homepage, https://github.com/microsoft/routeros-scanner
Project-URL: Bug Tracker, https://github.com/microsoft/routeros-scanner/issues
Author-email: Noa Frumovich <noaf@microsoft.com>
License:     MIT License
Classifier: License :: OSI Approved :: MIT License
Classifier: Operating System :: OS Independent
Classifier: Programming Language :: Python :: 3
Requires-Python: >=3.8
Requires-Dist: paramiko==2.9.2
Requires-Dist: requests==2.27.1
Requires-Dist: retry==0.9.2
Requires-Dist: six==1.16.0
